LICENSE
MANIFEST.in
README.rst
install_requires.txt
setup.py
tests_require.txt
graphite_query.egg-info/PKG-INFO
graphite_query.egg-info/SOURCES.txt
graphite_query.egg-info/dependency_links.txt
graphite_query.egg-info/not-zip-safe
graphite_query.egg-info/requires.txt
graphite_query.egg-info/top_level.txt
graphitequery/__init__.py
graphitequery/carbonlink.py
graphitequery/intervals.py
graphitequery/logger.py
graphitequery/node.py
graphitequery/readers.py
graphitequery/remote_storage.py
graphitequery/settings.py
graphitequery/storage.py
graphitequery/util.py
graphitequery/finders/__init__.py
graphitequery/finders/ceres.py
graphitequery/finders/standard.py
graphitequery/query/__init__.py
graphitequery/query/attime.py
graphitequery/query/datalib.py
graphitequery/query/evaluator.py
graphitequery/query/functions.py
graphitequery/query/grammar.py
graphitequery/query/hashing.py