Metadata-Version: 1.1
Name: graphite-query
Version: 0.11.3
Summary: Utilities for querying graphite's database
Home-page: https://github.com/edin1/graphite-query
Author: edin1, based on Chris Davis's graphite-weband Bruno Renié's graphite-api
Author-email: UNKNOWN
License: Apache Software License 2.0
Platform: UNKNOWN
Classifier: Development Status :: 3 - Alpha
Classifier: Intended Audience :: Developers
Classifier: Intended Audience :: System Administrators
Classifier: License :: OSI Approved :: Apache Software License
Classifier: Operating System :: OS Independent
Classifier: Programming Language :: Python
Classifier: Programming Language :: Python :: 2
Classifier: Programming Language :: Python :: 2.6
Classifier: Programming Language :: Python :: 2.7
Classifier: Topic :: Scientific/Engineering :: Information Analysis
Classifier: Topic :: System :: Monitoring
